LICENSE
README.md
setup.cfg
setup.py
PyAlphabet/AlphabetLetters.py
PyAlphabet/__init__.py
PyAlphabet.egg-info/PKG-INFO
PyAlphabet.egg-info/SOURCES.txt
PyAlphabet.egg-info/dependency_links.txt
PyAlphabet.egg-info/top_level.txt