Metadata-Version: 2.1
Name: PyAlphabet
Version: 1.1
Home-page: https://github.com/Shedrjoinzz/Scrambler-PyAlphabet
Download-URL: https://github.com/Shedrjoinzz/Scrambler-PyAlphabet/zipball/master/
Author: Scrambler
Author-email: vagifhalilov02@gmail.com
Classifier: Programming Language :: Python :: 3
Classifier: License :: OSI Approved :: MIT License
Classifier: Operating System :: OS Independent
Requires-Python: >=3.6
License-File: LICENSE
